schemautil/__init__.py
schemautil/make.py
bfg_schemautil-0.2.0.dist-info/METADATA
bfg_schemautil-0.2.0.dist-info/WHEEL
bfg_schemautil-0.2.0.dist-info/RECORD
