Metadata-Version: 2.4
Name: bfg-schemautil
Version: 0.2.0
Summary: A set of utilities to generate JSON Schema from simple JSON objects
Author-email: Lei Zhao <8961794+leizha@users.noreply.github.com>
Requires-Python: >=3.10
